renderer/__init__.py
renderer/classes.py
renderer/examples.py
3d_renderer-0.0.6.dist-info/LICENSE
3d_renderer-0.0.6.dist-info/METADATA
3d_renderer-0.0.6.dist-info/WHEEL
3d_renderer-0.0.6.dist-info/top_level.txt
3d_renderer-0.0.6.dist-info/RECORD
