Metadata-Version: 2.1
Name: 3d-renderer
Version: 0.0.6
Summary: A Python module that renders 3D objects as pygame surfaces.
Home-page: https://github.com/HuangPatrick16777216/3d_renderer
Author: Patrick Huang
Author-email: huangpatrick16777216@gmail.com
License: UNKNOWN
Platform: UNKNOWN
Classifier: Programming Language :: Python :: 3
Classifier: License :: OSI Approved :: GNU General Public License v2 or later (GPLv2+)
Classifier: Operating System :: OS Independent
Requires-Dist: pygame
